MANIFEST.in
README.md
setup.py
api/__init__.py
api/config.py
api/dkim.py
api/errors.py
api/parameters.py
api/resolver.py
api/server.py
api/utils.py
api/auth/__init__.py
api/auth/authentication.py
api/auth/models.py
api/auth/registration.py
api/auth/utils.py
api/auth/views.py
api/search/__init__.py
api/search/attributes_index.py
api/search/basic_index.py
api/search/config.py
api/search/db.py
api/search/fetch_data.py
api/search/server.py
api/search/substring_search.py
api/search/utils.py
api/tests/__init__.py
api/tests/api_tests.py
api/tests/resolver_tests.py
api/tests/search_tests.py
bin/__init__.py
bin/blockstack-core
bin/blockstack-server
bin/blockstack-snapshots
blockstack/__init__.py
blockstack/blockstackd.py
blockstack/version.py
blockstack.egg-info/PKG-INFO
blockstack.egg-info/SOURCES.txt
blockstack.egg-info/dependency_links.txt
blockstack.egg-info/not-zip-safe
blockstack.egg-info/requires.txt
blockstack.egg-info/top_level.txt
blockstack/data/__init__.py
blockstack/data/blockchain-airdrop-2020.csv
blockstack/lib/__init__.py
blockstack/lib/atlas.py
blockstack/lib/audit.py
blockstack/lib/b40.py
blockstack/lib/c32.py
blockstack/lib/client.py
blockstack/lib/config.py
blockstack/lib/fast_sync.py
blockstack/lib/genesis_block.py
blockstack/lib/hashing.py
blockstack/lib/queue.py
blockstack/lib/rpc.py
blockstack/lib/schemas.py
blockstack/lib/scripts.py
blockstack/lib/snv.py
blockstack/lib/subdomains.py
blockstack/lib/util.py
blockstack/lib/nameset/__init__.py
blockstack/lib/nameset/db.py
blockstack/lib/nameset/namedb.py
blockstack/lib/nameset/virtualchain_hooks.py
blockstack/lib/operations/__init__.py
blockstack/lib/operations/announce.py
blockstack/lib/operations/nameimport.py
blockstack/lib/operations/namespacepreorder.py
blockstack/lib/operations/namespaceready.py
blockstack/lib/operations/namespacereveal.py
blockstack/lib/operations/preorder.py
blockstack/lib/operations/register.py
blockstack/lib/operations/revoke.py
blockstack/lib/operations/tokentransfer.py
blockstack/lib/operations/transfer.py
blockstack/lib/operations/update.py
blockstack/lib/storage/__init__.py
blockstack/lib/storage/auth.py
blockstack/lib/storage/crawl.py