Metadata-Version: 1.1
Name: blockstack
Version: 22.0.0.0
Summary: Name registrations on the Bitcoin blockchain with external storage
Home-page: https://github.com/blockstack/blockstack-core
Author: Blockstack.org
Author-email: support@blockstack.org
License: GPLv3
Download-URL: https://github.com/blockstack/blockstore/archive/master.zip
Keywords: blockchain bitcoin btc cryptocurrency name key value store data
Platform: UNKNOWN
Classifier: Intended Audience :: Developers
Classifier: License :: OSI Approved :: GNU General Public License v3 (GPLv3)
Classifier: Operating System :: OS Independent
Classifier: Programming Language :: Python :: 2 :: Only
Classifier: Topic :: Internet
Classifier: Topic :: Security :: Cryptography
Classifier: Topic :: Software Development :: Libraries :: Python Modules
